verifai_sdk/__init__.py
verifai_sdk/document.py
verifai_sdk/id_model.py
verifai_sdk/pdf_support.py
verifai_sdk/service.py
verifai_sdk/version.py
verifai_sdk-2.1.2.dist-info/LICENSE
verifai_sdk-2.1.2.dist-info/METADATA
verifai_sdk-2.1.2.dist-info/WHEEL
verifai_sdk-2.1.2.dist-info/top_level.txt
verifai_sdk-2.1.2.dist-info/RECORD
